media/__init__.py
media/data/__init__.py
media/data/dates.py
media/data/nouns.py
media/data/media/__init__.py
media/data/media/internal.py
media/data/media/contents/__init__.py
media/data/media/contents/internal.py
media/data/media/contents/audio/__init__.py
media/data/media/contents/audio/album/__init__.py
media/data/media/contents/audio/album/catalog.py
media/data/media/contents/audio/album/classification.py
media/data/media/contents/audio/album/internal.py
media/data/media/contents/audio/album/technical.py
media/data/media/contents/audio/elements/__init__.py
media/data/media/contents/audio/elements/dialogue.py
media/data/media/contents/audio/elements/internal.py
media/data/media/contents/audio/elements/song.py
media/data/media/contents/generic/__init__.py
media/data/media/contents/generic/catalog.py
media/data/media/contents/generic/keywords.py
media/data/media/contents/generic/story/__init__.py
media/data/media/contents/generic/story/characters.py
media/data/media/contents/generic/story/internal.py
media/data/media/contents/genericv/__init__.py
media/data/media/contents/genericv/technical.py
media/data/media/contents/genericv/variants.py
media/data/media/contents/genericv/crew/__init__.py
media/data/media/contents/genericv/crew/cast.py
media/data/media/contents/genericv/crew/internal.py
media/data/media/contents/movie/__init__.py
media/data/media/contents/movie/classification.py
media/data/media/contents/movie/internal.py
media/data/media/library/__init__.py
media/data/media/library/filing.py
media/data/media/library/instances.py
media/data/media/library/internal.py
media/data/media/medium/__init__.py
media/data/media/medium/internal.py
media/data/media/medium/inventory.py
media/data/media/medium/productid.py
media/data/media/medium/productspecs.py
media/data/media/medium/release.py
media/data/media/meta/__init__.py
media/data/media/meta/authorship.py
media/fileops/__init__.py
media/fileops/filenames.py
media/fileops/loader.py
media/fileops/repo.py
medialibrary-0.2.9.dist-info/licenses/LICENSE
medialibrary-0.2.9.dist-info/METADATA
medialibrary-0.2.9.dist-info/WHEEL
medialibrary-0.2.9.dist-info/top_level.txt
medialibrary-0.2.9.dist-info/RECORD
