Metadata-Version: 2.4
Name: medialibrary
Version: 0.2.9
Summary: Package for reading vtmedia XML files describing a movie/music media library
Author-email: Chris J <cjcodeproj@fastmail.com>
License: MIT License
Project-URL: homepage, https://github.com/cjcodeproj/medialibrary
Project-URL: bug tracker, https://github.com/cjcodeproj/medialibrary/issues
Project-URL: repository, https://github.com/cjcodeproj/medialibrary
Project-URL: changelog, https://github.com/cjcodeproj/medialibrary/blob/main/CHANGELOG.md
Keywords: xml,movies,dvds,music,cds,albums
Classifier: Development Status :: 4 - Beta
Classifier: Environment :: Console
Classifier: Intended Audience :: Developers
Classifier: License :: OSI Approved :: MIT License
Classifier: Operating System :: OS Independent
Classifier: Programming Language :: Python :: 3
Classifier: Topic :: Text Processing :: Markup :: XML
Classifier: Topic :: Multimedia
Classifier: Topic :: Multimedia :: Sound/Audio
Classifier: Topic :: Multimedia :: Video
Requires-Python: >3.8
License-File: LICENSE
Dynamic: license-file
